{
  "schema_version": "1.0",
  "snapshot_id": "SDU_MULTIREPO_SNAPSHOT_20260623_0135",
  "created_at_utc": "2026-06-23T01:35:22Z",
  "version": "v0.6.0-rc1",
  "mode": "FULL_CABINA_GOVERNED_LIVE_ENABLED_GATED",
  "control_repo": "universo-rey/projec-cdx",
  "control_commit": "9545bc07",
  "control_branch": "codex/runtime-versioning-snapshots",
  "external_writes": false,
  "push": false,
  "pull_request": false,
  "workflow_dispatch": false,
  "live_surface_execution": false,
  "summary": {
    "repos_total": 16,
    "local_paths_present": 16,
    "git_repos": 15,
    "non_git_surfaces": 1,
    "clean_git_repos": 12,
    "dirty_git_repos": 3,
    "native_snapshot_repos": 1,
    "central_snapshot_repos": 16
  },
  "agents": [
    "thot-tecnico",
    "maat-cumplimiento",
    "horus-riesgo",
    "anubis-gate",
    "seshat-normativa",
    "sentinel-runtime",
    "narrador-normativo",
    "EATOMIC"
  ],
  "repos": [
    {
      "repo": "universo-rey/projec-cdx",
      "ring": "ANILLO_0_CONTROL",
      "path": "C:/Users/enzo1/PROJEC CDX",
      "is_git": true,
      "branch": "codex/runtime-versioning-snapshots",
      "head": "9545bc07",
      "working_tree": "CLEAN",
      "native_snapshot": true,
      "central_snapshot": true,
      "decision": "SNAPSHOT_NATIVE_UPDATED"
    },
    {
      "repo": "universo-rey/agents-root",
      "ring": "ANILLO_0_CONTROL",
      "path": "C:/CEO/agents",
      "is_git": false,
      "branch": "NO_LOCAL",
      "head": "NO_LOCAL",
      "working_tree": "NOT_GIT",
      "native_snapshot": false,
      "central_snapshot": true,
      "decision": "OBSERVED_NON_GIT_SURFACE"
    },
    {
      "repo": "universo-rey/codex-root",
      "ring": "ANILLO_0_CONTROL",
      "path": "C:/Users/enzo1/.codex",
      "is_git": true,
      "branch": "main",
      "head": "eed6262",
      "working_tree": "DIRTY",
      "dirty_count": 21,
      "native_snapshot": false,
      "central_snapshot": true,
      "decision": "OBSERVED_DIRTY_NO_CHILD_MUTATION"
    },
    {
      "repo": "universo-rey/cabina-universal-d",
      "ring": "ANILLO_1_CANON_13",
      "path": "C:/Users/enzo1/Documents/GitHub/cabina-universal-d",
      "is_git": true,
      "branch": "codex/pr96-total-local-alignment-20260622",
      "head": "28baec3",
      "working_tree": "DIRTY",
      "dirty_count": 21,
      "native_snapshot": false,
      "central_snapshot": true,
      "decision": "OBSERVED_DIRTY_NO_CHILD_MUTATION"
    },
    {
      "repo": "SeshatSgin/cdf-soluciones",
      "ring": "ANILLO_1_CANON_13",
      "path": "C:/Users/enzo1/Documents/GitHub/cdf-soluciones",
      "is_git": true,
      "branch": "codex/cdf-seshat-context-evidence-split-20260617",
      "head": "2ccd77d",
      "working_tree": "CLEAN",
      "native_snapshot": false,
      "central_snapshot": true,
      "decision": "CENTRAL_SNAPSHOT_ONLY"
    },
    {
      "repo": "SeshatSgin/jara-consultores",
      "ring": "ANILLO_1_CANON_13",
      "path": "C:/Users/enzo1/Documents/GitHub/jara-consultores",
      "is_git": true,
      "branch": "codex/readme-lane-atomica-20260617",
      "head": "88676e0",
      "working_tree": "CLEAN",
      "native_snapshot": false,
      "central_snapshot": true,
      "decision": "CENTRAL_SNAPSHOT_ONLY"
    },
    {
      "repo": "universo-rey/microsoft-agents-governed-lab",
      "ring": "ANILLO_1_CANON_13",
      "path": "C:/Users/enzo1/Documents/GitHub/microsoft-agents-governed-lab",
      "is_git": true,
      "branch": "codex/readme-lane-atomica-20260617",
      "head": "d1ca48c",
      "working_tree": "CLEAN",
      "native_snapshot": false,
      "central_snapshot": true,
      "decision": "CENTRAL_SNAPSHOT_ONLY"
    },
    {
      "repo": "SeshatSgin/modo-on-foundation",
      "ring": "ANILLO_1_CANON_13",
      "path": "C:/Users/enzo1/Documents/GitHub/modo-on-foundation",
      "is_git": true,
      "branch": "codex/readme-lane-atomica-20260617",
      "head": "fb4d9b4",
      "working_tree": "CLEAN",
      "native_snapshot": false,
      "central_snapshot": true,
      "decision": "CENTRAL_SNAPSHOT_ONLY"
    },
    {
      "repo": "universo-rey/organizacion",
      "ring": "ANILLO_1_CANON_13",
      "path": "C:/Users/enzo1/Documents/GitHub/organizacion",
      "is_git": true,
      "branch": "codex/readme-lane-atomica-20260617",
      "head": "7cf4a86",
      "working_tree": "CLEAN",
      "native_snapshot": false,
      "central_snapshot": true,
      "decision": "CENTRAL_SNAPSHOT_ONLY"
    },
    {
      "repo": "SeshatSgin/sdu-canon",
      "ring": "ANILLO_1_CANON_13",
      "path": "C:/Users/enzo1/Documents/GitHub/sdu-canon",
      "is_git": true,
      "branch": "codex/lane-a-sdu-canon-context-20260617",
      "head": "54e1317",
      "working_tree": "CLEAN",
      "native_snapshot": false,
      "central_snapshot": true,
      "decision": "CENTRAL_SNAPSHOT_ONLY"
    },
    {
      "repo": "SeshatSgin/seshat-bootstrap-sdu-cn",
      "ring": "ANILLO_1_CANON_13",
      "path": "C:/Users/enzo1/Documents/GitHub/seshat-bootstrap-sdu-cn",
      "is_git": true,
      "branch": "codex/seshat-prompt-drafts-canon-guarded",
      "head": "b0b93bd",
      "working_tree": "CLEAN",
      "native_snapshot": false,
      "central_snapshot": true,
      "decision": "CENTRAL_SNAPSHOT_ONLY"
    },
    {
      "repo": "universo-rey/Sgin",
      "ring": "ANILLO_1_CANON_13",
      "path": "C:/Users/enzo1/Documents/GitHub/Sgin",
      "is_git": true,
      "branch": "main",
      "head": "cfb494b",
      "working_tree": "DIRTY",
      "dirty_count": 31,
      "native_snapshot": false,
      "central_snapshot": true,
      "decision": "OBSERVED_DIRTY_NO_CHILD_MUTATION"
    },
    {
      "repo": "SeshatSgin/sgin-cumplimiento",
      "ring": "ANILLO_1_CANON_13",
      "path": "C:/Users/enzo1/Documents/GitHub/sgin-cumplimiento",
      "is_git": true,
      "branch": "codex/readme-lane-atomica-20260617",
      "head": "ed506d9",
      "working_tree": "CLEAN",
      "native_snapshot": false,
      "central_snapshot": true,
      "decision": "CENTRAL_SNAPSHOT_ONLY"
    },
    {
      "repo": "SeshatSgin/tcu-agentic-runtime-control",
      "ring": "ANILLO_1_CANON_13",
      "path": "C:/Users/enzo1/Documents/GitHub/tcu-agentic-runtime-control",
      "is_git": true,
      "branch": "codex/readme-lane-atomica-20260617",
      "head": "96e6808",
      "working_tree": "CLEAN",
      "native_snapshot": false,
      "central_snapshot": true,
      "decision": "CENTRAL_SNAPSHOT_ONLY"
    },
    {
      "repo": "SeshatSgin/tge-agentic-runtime-control-escribania",
      "ring": "ANILLO_1_CANON_13",
      "path": "C:/Users/enzo1/Documents/GitHub/tge-agentic-runtime-control-escribania",
      "is_git": true,
      "branch": "codex/readme-lane-atomica-20260617",
      "head": "63dc293",
      "working_tree": "CLEAN",
      "native_snapshot": false,
      "central_snapshot": true,
      "decision": "CENTRAL_SNAPSHOT_ONLY"
    },
    {
      "repo": "SeshatSgin/torre-gemela-escribania",
      "ring": "ANILLO_1_CANON_13",
      "path": "C:/Users/enzo1/Documents/GitHub/torre-gemela-escribania",
      "is_git": true,
      "branch": "codex/readme-lane-atomica-20260617",
      "head": "76bbded",
      "working_tree": "CLEAN",
      "native_snapshot": false,
      "central_snapshot": true,
      "decision": "CENTRAL_SNAPSHOT_ONLY"
    }
  ],
  "stop_condition": "STOP if asked to mutate child repos without per-repo owner, rollback, postcheck and evidence"
}
