{"nodes": [{"id": "c_users_enzo1_projec_cdx_procesos_complementos_on_demand_md", "label": "complementos-on-demand.md", "file_type": "document", "source_file": "procesos/complementos-on-demand.md", "source_location": "L1"}, {"id": "procesos_complementos_on_demand_complementos_on_demand", "label": "Complementos On Demand", "file_type": "document", "source_file": "procesos/complementos-on-demand.md", "source_location": "L1"}, {"id": "procesos_complementos_on_demand_entrada", "label": "Entrada", "file_type": "document", "source_file": "procesos/complementos-on-demand.md", "source_location": "L3"}, {"id": "procesos_complementos_on_demand_pasos", "label": "Pasos", "file_type": "document", "source_file": "procesos/complementos-on-demand.md", "source_location": "L7"}, {"id": "procesos_complementos_on_demand_salida", "label": "Salida", "file_type": "document", "source_file": "procesos/complementos-on-demand.md", "source_location": "L18"}, {"id": "procesos_complementos_on_demand_stop_condition", "label": "Stop Condition", "file_type": "document", "source_file": "procesos/complementos-on-demand.md", "source_location": "L22"}], "edges": [{"source": "c_users_enzo1_projec_cdx_procesos_complementos_on_demand_md", "target": "procesos_complementos_on_demand_complementos_on_demand", "relation": "contains", "confidence": "EXTRACTED", "source_file": "procesos/complementos-on-demand.md", "source_location": "L1", "weight": 1.0}, {"source": "procesos_complementos_on_demand_complementos_on_demand", "target": "procesos_complementos_on_demand_entrada", "relation": "contains", "confidence": "EXTRACTED", "source_file": "procesos/complementos-on-demand.md", "source_location": "L3", "weight": 1.0}, {"source": "procesos_complementos_on_demand_complementos_on_demand", "target": "procesos_complementos_on_demand_pasos", "relation": "contains", "confidence": "EXTRACTED", "source_file": "procesos/complementos-on-demand.md", "source_location": "L7", "weight": 1.0}, {"source": "procesos_complementos_on_demand_complementos_on_demand", "target": "procesos_complementos_on_demand_salida", "relation": "contains", "confidence": "EXTRACTED", "source_file": "procesos/complementos-on-demand.md", "source_location": "L18", "weight": 1.0}, {"source": "procesos_complementos_on_demand_complementos_on_demand", "target": "procesos_complementos_on_demand_stop_condition", "relation": "contains", "confidence": "EXTRACTED", "source_file": "procesos/complementos-on-demand.md", "source_location": "L22", "weight": 1.0}], "input_tokens": 0, "output_tokens": 0}