{"nodes": [{"id": "c_users_enzo1_projec_cdx_dataverse_registro_bloqueos_md", "label": "REGISTRO_BLOQUEOS.md", "file_type": "document", "source_file": "dataverse/REGISTRO_BLOQUEOS.md", "source_location": "L1"}, {"id": "dataverse_registro_bloqueos_registro_de_bloqueos_dataverse", "label": "Registro De Bloqueos Dataverse", "file_type": "document", "source_file": "dataverse/REGISTRO_BLOQUEOS.md", "source_location": "L1"}, {"id": "dataverse_registro_bloqueos_regla_practica", "label": "Regla Practica", "file_type": "document", "source_file": "dataverse/REGISTRO_BLOQUEOS.md", "source_location": "L5"}, {"id": "dataverse_registro_bloqueos_modelo_minimo", "label": "Modelo Minimo", "file_type": "document", "source_file": "dataverse/REGISTRO_BLOQUEOS.md", "source_location": "L11"}, {"id": "dataverse_registro_bloqueos_blocker_case", "label": "blocker_case", "file_type": "document", "source_file": "dataverse/REGISTRO_BLOQUEOS.md", "source_location": "L13"}, {"id": "dataverse_registro_bloqueos_human_decision", "label": "human_decision", "file_type": "document", "source_file": "dataverse/REGISTRO_BLOQUEOS.md", "source_location": "L22"}, {"id": "dataverse_registro_bloqueos_evidence_required", "label": "evidence_required", "file_type": "document", "source_file": "dataverse/REGISTRO_BLOQUEOS.md", "source_location": "L29"}, {"id": "dataverse_registro_bloqueos_resolution_action", "label": "resolution_action", "file_type": "document", "source_file": "dataverse/REGISTRO_BLOQUEOS.md", "source_location": "L35"}, {"id": "dataverse_registro_bloqueos_ejemplos_de_uso", "label": "Ejemplos De Uso", "file_type": "document", "source_file": "dataverse/REGISTRO_BLOQUEOS.md", "source_location": "L41"}, {"id": "dataverse_registro_bloqueos_cierre", "label": "Cierre", "file_type": "document", "source_file": "dataverse/REGISTRO_BLOQUEOS.md", "source_location": "L52"}], "edges": [{"source": "c_users_enzo1_projec_cdx_dataverse_registro_bloqueos_md", "target": "dataverse_registro_bloqueos_registro_de_bloqueos_dataverse", "relation": "contains", "confidence": "EXTRACTED", "source_file": "dataverse/REGISTRO_BLOQUEOS.md", "source_location": "L1", "weight": 1.0}, {"source": "dataverse_registro_bloqueos_registro_de_bloqueos_dataverse", "target": "dataverse_registro_bloqueos_regla_practica", "relation": "contains", "confidence": "EXTRACTED", "source_file": "dataverse/REGISTRO_BLOQUEOS.md", "source_location": "L5", "weight": 1.0}, {"source": "dataverse_registro_bloqueos_registro_de_bloqueos_dataverse", "target": "dataverse_registro_bloqueos_modelo_minimo", "relation": "contains", "confidence": "EXTRACTED", "source_file": "dataverse/REGISTRO_BLOQUEOS.md", "source_location": "L11", "weight": 1.0}, {"source": "dataverse_registro_bloqueos_modelo_minimo", "target": "dataverse_registro_bloqueos_blocker_case", "relation": "contains", "confidence": "EXTRACTED", "source_file": "dataverse/REGISTRO_BLOQUEOS.md", "source_location": "L13", "weight": 1.0}, {"source": "dataverse_registro_bloqueos_modelo_minimo", "target": "dataverse_registro_bloqueos_human_decision", "relation": "contains", "confidence": "EXTRACTED", "source_file": "dataverse/REGISTRO_BLOQUEOS.md", "source_location": "L22", "weight": 1.0}, {"source": "dataverse_registro_bloqueos_modelo_minimo", "target": "dataverse_registro_bloqueos_evidence_required", "relation": "contains", "confidence": "EXTRACTED", "source_file": "dataverse/REGISTRO_BLOQUEOS.md", "source_location": "L29", "weight": 1.0}, {"source": "dataverse_registro_bloqueos_modelo_minimo", "target": "dataverse_registro_bloqueos_resolution_action", "relation": "contains", "confidence": "EXTRACTED", "source_file": "dataverse/REGISTRO_BLOQUEOS.md", "source_location": "L35", "weight": 1.0}, {"source": "dataverse_registro_bloqueos_registro_de_bloqueos_dataverse", "target": "dataverse_registro_bloqueos_ejemplos_de_uso", "relation": "contains", "confidence": "EXTRACTED", "source_file": "dataverse/REGISTRO_BLOQUEOS.md", "source_location": "L41", "weight": 1.0}, {"source": "dataverse_registro_bloqueos_registro_de_bloqueos_dataverse", "target": "dataverse_registro_bloqueos_cierre", "relation": "contains", "confidence": "EXTRACTED", "source_file": "dataverse/REGISTRO_BLOQUEOS.md", "source_location": "L52", "weight": 1.0}], "input_tokens": 0, "output_tokens": 0}