{
  "command": "CABINA_LOCAL_FILES_RECONCILIATION_AND_NOISE_REDUCTION_G1",
  "status": "CABINA_REPO_BOUNDARY_MAP_READY",
  "generated_at": "2026-06-26T07:07:32Z",
  "repo_boundaries": [
    {
      "repo": "root",
      "name": "project-cdx",
      "class": "root_junction_git_worktree",
      "path": ".",
      "requested_root": "C:\\CEO\\project-cdx",
      "physical_target": "C:\\Users\\enzo1\\PROJEC CDX",
      "git_read": true,
      "git_error": null,
      "branch": "codex/m365-escribania-dataverse-restore",
      "head": "e9fcd7e949ebe2ed024d6bdd2cb6945d95f34b11",
      "remote": "NO_UPSTREAM_OBSERVED",
      "status_count": 26,
      "clean": false,
      "core_worktree": null,
      "absorb_policy": "ROOT_ONLY_DO_NOT_REANCHOR"
    },
    {
      "repo": "nested",
      "name": ".cabina",
      "class": "ignored_runtime_nested_repo",
      "path": ".cabina",
      "requested_root": "C:\\CEO\\project-cdx\\.cabina",
      "physical_target": "local_ignored_runtime_surface",
      "git_read": "metadata_only_from_agent",
      "git_error": "git_cli_blocked_by_dubious_ownership_in_agent_scan",
      "branch": "main",
      "head": "5d1ceba71e4f494cdcf2e86b624edd4dddc6f9d3",
      "remote": "NO_CONSTA",
      "status_count": null,
      "clean": null,
      "core_worktree": null,
      "absorb_policy": "DO_NOT_ABSORB"
    },
    {
      "repo": "nested_group",
      "name": "outputs-ceo-suite-test-temp-repos",
      "class": "generated_pytest_temp_repos",
      "path": "outputs\\ceo-suite-test\\*",
      "requested_root": "C:\\CEO\\project-cdx\\outputs\\ceo-suite-test",
      "physical_target": "generated_outputs",
      "git_read": "count_from_agent_metadata",
      "git_error": null,
      "branch": "NO_CONSTA",
      "head": "NO_CONSTA",
      "remote": "NO_CONSTA",
      "status_count": 28,
      "clean": null,
      "core_worktree": null,
      "absorb_policy": "DO_NOT_ABSORB_TREAT_AS_GENERATED_TEST_NOISE"
    },
    {
      "repo": "dependency_boundary",
      "name": "node_modules",
      "class": "junction_dependency_surface",
      "path": "node_modules",
      "requested_root": "C:\\CEO\\project-cdx\\node_modules",
      "physical_target": "junction_not_followed",
      "git_read": false,
      "git_error": null,
      "branch": "N_A",
      "head": "N_A",
      "remote": "N_A",
      "status_count": null,
      "clean": null,
      "core_worktree": null,
      "absorb_policy": "DO_NOT_TRAVERSE_OR_CLEAN_TARGET"
    }
  ],
  "nested_repo_count": 29,
  "boundary_count": 4,
  "linked_worktrees_count_observed_by_agent": 9,
  "frontier": {
    "local_first": true,
    "no_delete": true,
    "no_move": true,
    "no_overwrite": true,
    "no_git_write": true,
    "no_remote": true,
    "no_live": true,
    "no_secret_read": true,
    "no_sdk_install": true,
    "no_core_worktree_change": true,
    "safe_apply_executed": false
  }
}